CHANGES.rst
LICENSE.txt
MANIFEST.in
README.rst
TODO.txt
setup.py
audiotracks/__init__.py
audiotracks/admin.py
audiotracks/feeds.py
audiotracks/forms.py
audiotracks/models.py
audiotracks/thumbs.py
audiotracks/urls.py
audiotracks/views.py
audiotracks/locale/fr/LC_MESSAGES/django.mo
audiotracks/locale/fr/LC_MESSAGES/django.po
audiotracks/static/mediaelement-2.8.2/background.png
audiotracks/static/mediaelement-2.8.2/bigplay.png
audiotracks/static/mediaelement-2.8.2/controls-ted.png
audiotracks/static/mediaelement-2.8.2/controls-wmp-bg.png
audiotracks/static/mediaelement-2.8.2/controls-wmp.png
audiotracks/static/mediaelement-2.8.2/controls.png
audiotracks/static/mediaelement-2.8.2/flashmediaelement.swf
audiotracks/static/mediaelement-2.8.2/jquery-1.7.2.min.js
audiotracks/static/mediaelement-2.8.2/loading.gif
audiotracks/static/mediaelement-2.8.2/mediaelement-and-player.min.js
audiotracks/static/mediaelement-2.8.2/mediaelementplayer.min.css
audiotracks/static/mediaelement-2.8.2/mejs-skins.css
audiotracks/static/mediaelement-2.8.2/silverlightmediaelement.xap
audiotracks/templates/_pagination.html
audiotracks/templates/audiotracks/_list_actions.html
audiotracks/templates/audiotracks/base.html
audiotracks/templates/audiotracks/confirm_delete.html
audiotracks/templates/audiotracks/detail.html
audiotracks/templates/audiotracks/edit.html
audiotracks/templates/audiotracks/latest.html
audiotracks/templates/audiotracks/listing_item.html
audiotracks/templates/audiotracks/mediaelement_base.html
audiotracks/templates/audiotracks/new.html
audiotracks/templates/audiotracks/player.js
audiotracks/templates/audiotracks/user_index.html
django_audiotracks.egg-info/PKG-INFO
django_audiotracks.egg-info/SOURCES.txt
django_audiotracks.egg-info/dependency_links.txt
django_audiotracks.egg-info/not-zip-safe
django_audiotracks.egg-info/requires.txt
django_audiotracks.egg-info/top_level.txt