Metadata-Version: 1.1
Name: django-audiotracks
Version: 0.2
Summary: A pluggable Django app to publish audio tracks
Home-page: https://github.com/amarandon/django-audiotracks
Author: Alex Marandon
Author-email: contact@alexmarandon.com
License: MIT
Keywords: django audio sound
Platform: UNKNOWN
Classifier: Development Status :: 3 - Alpha
Classifier: Environment :: Web Environment
Classifier: Intended Audience :: Developers
Classifier: License :: OSI Approved :: MIT License
Classifier: Operating System :: OS Independent
Classifier: Programming Language :: Python
Classifier: Framework :: Django
